pyoperon/__init__.py
pyoperon/pyoperon.cpython-38-x86_64-linux-gnu.so
pyoperon/sklearn.py
pyoperon.libs/libxxhash-3b878866.so.0.8.2
pyoperon.libs/libzstd-76b78bac.so.1.4.4
pyoperon-0.5.0.dist-info/LICENSE
pyoperon-0.5.0.dist-info/METADATA
pyoperon-0.5.0.dist-info/WHEEL
pyoperon-0.5.0.dist-info/top_level.txt
pyoperon-0.5.0.dist-info/RECORD
